sagace_sdk/__init__.py
sagace_sdk/auth/__init__.py
sagace_sdk/auth/manager.py
sagace_sdk/auth/provider/__init__.py
sagace_sdk/auth/provider/file_provider.py
sagace_sdk/auth/provider/provider.py
sagace_sdk/auth/provider/request_manager.py
sagace_sdk/data_models/__init__.py
sagace_sdk/data_models/model.py
sagace_sdk/data_models/auth/__init__.py
sagace_sdk/data_models/auth/login_request.py
sagace_sdk/enums/__init__.py
sagace_sdk/enums/filter_operator.py
sagace_sdk/enums/query_condition.py
sagace_sdk/enums/query_order.py
sagace_sdk/exceptions/__init__.py
sagace_sdk/exceptions/auth_provider_exception.py
sagace_sdk/exceptions/request_exception.py
sagace_sdk/exceptions/url_search_exception.py
sagace_sdk/modules/__init__.py
sagace_sdk/modules/base/__init__.py
sagace_sdk/modules/base/user.py
sagace_sdk/utils/__init__.py
sagace_sdk/utils/configuration.py
sagace_sdk/utils/formatting.py
sagace_sdk/utils/url.py
sagace_sdk/utils/query/__init__.py
sagace_sdk/utils/query/filter.py
sagace_sdk/utils/query/order.py
sagace_sdk/utils/query/pagination.py
sagace_sdk/utils/query/query_request.py
sagace_sdk-0.1.0.2.dist-info/LICENSE
sagace_sdk-0.1.0.2.dist-info/METADATA
sagace_sdk-0.1.0.2.dist-info/WHEEL
sagace_sdk-0.1.0.2.dist-info/top_level.txt
sagace_sdk-0.1.0.2.dist-info/RECORD
