Metadata-Version: 2.1
Name: sagace_sdk
Version: 0.1.0.2
Summary: Pacote de métodos usados para implementação da API de acesso ao SAGACE
Home-page: https://gitlab.com/ampere.consultoria/sagace-python-sdk.git
Author: Diego Isaac Haruwo Yosiura
Author-email: diego@ampereconsultoria.com.br
Project-URL: Bug Tracker, https://gitlab.com/ampere.consultoria/sagace-python-sdk/-/issues
Classifier: Programming Language :: Python :: 3
Classifier: License :: OSI Approved :: MIT License
Classifier: Operating System :: OS Independent
Requires-Python: >=3.6
License-File: LICENSE
Requires-Dist: requests
Requires-Dist: requests-toolbelt
